agenbits/__init__.py
agenbits/core/__init__.py
agenbits/core/converter.py
agenbits/core/decoder.py
agenbits/core/detector.py
agenbits/core/downloader.py
agenbits/interfaces/__init__.py
agenbits/interfaces/audio.py
agenbits/interfaces/binary.py
agenbits/interfaces/excel.py
agenbits/interfaces/image.py
agenbits/interfaces/text.py
agenbits/interfaces/video.py
agenbits/utils/__init__.py
agenbits/utils/file_utils.py
agenbits-0.1.2.dist-info/LICENSE.md
agenbits-0.1.2.dist-info/METADATA
agenbits-0.1.2.dist-info/WHEEL
agenbits-0.1.2.dist-info/top_level.txt
agenbits-0.1.2.dist-info/RECORD
