Metadata-Version: 2.1
Name: agenbits
Version: 0.1.2
Summary: A library to fetch, convert, and decode binary input data for ML models.
Home-page: https://github.com/dunkdumb/agenbyte
Author: Enos
Author-email: enosuppada2005@gmail.com
Classifier: Programming Language :: Python :: 3
Classifier: License :: OSI Approved :: MIT License
Classifier: Operating System :: OS Independent
Requires-Python: >=3.7
License-File: LICENSE.md
Requires-Dist: requests
Requires-Dist: pandas
Requires-Dist: openpyxl
Requires-Dist: Pillow
Requires-Dist: numpy
Requires-Dist: soundfile
Requires-Dist: opencv-python
